st_map_polygon_extract/__init__.py
st_map_polygon_extract/example.py
st_map_polygon_extract/frontend/build/asset-manifest.json
st_map_polygon_extract/frontend/build/bootstrap.min.css
st_map_polygon_extract/frontend/build/index.html
st_map_polygon_extract/frontend/build/static/css/main.6d43e5ed.css
st_map_polygon_extract/frontend/build/static/css/main.6d43e5ed.css.map
st_map_polygon_extract/frontend/build/static/js/main.2d8f45ad.js
st_map_polygon_extract/frontend/build/static/js/main.2d8f45ad.js.LICENSE.txt
st_map_polygon_extract/frontend/build/static/js/main.2d8f45ad.js.map
st_map_polygon_extract/frontend/build/static/media/spritesheet.a4e0eb7ad904a4858361.svg
streamlit_map_polygon_extract-0.0.3.dist-info/LICENSE
streamlit_map_polygon_extract-0.0.3.dist-info/METADATA
streamlit_map_polygon_extract-0.0.3.dist-info/WHEEL
streamlit_map_polygon_extract-0.0.3.dist-info/top_level.txt
streamlit_map_polygon_extract-0.0.3.dist-info/RECORD
